{"nodes": [{"id": "c_users_hp_desktop_driprank_src_components_leaderboard_weeklytimer_jsx", "label": "WeeklyTimer.jsx", "file_type": "code", "source_file": "C:\\Users\\HP\\Desktop\\driprank\\src\\components\\leaderboard\\WeeklyTimer.jsx", "source_location": "L1"}, {"id": "leaderboard_weeklytimer_getsecondsuntilmonday", "label": "getSecondsUntilMonday()", "file_type": "code", "source_file": "C:\\Users\\HP\\Desktop\\driprank\\src\\components\\leaderboard\\WeeklyTimer.jsx", "source_location": "L4"}, {"id": "leaderboard_weeklytimer_fmt", "label": "fmt()", "file_type": "code", "source_file": "C:\\Users\\HP\\Desktop\\driprank\\src\\components\\leaderboard\\WeeklyTimer.jsx", "source_location": "L14"}, {"id": "leaderboard_weeklytimer_seg", "label": "Seg()", "file_type": "code", "source_file": "C:\\Users\\HP\\Desktop\\driprank\\src\\components\\leaderboard\\WeeklyTimer.jsx", "source_location": "L22"}, {"id": "leaderboard_weeklytimer_weeklytimer", "label": "WeeklyTimer()", "file_type": "code", "source_file": "C:\\Users\\HP\\Desktop\\driprank\\src\\components\\leaderboard\\WeeklyTimer.jsx", "source_location": "L35"}], "edges": [{"source": "c_users_hp_desktop_driprank_src_components_leaderboard_weeklytimer_jsx", "target": "react", "relation": "imports_from", "context": "import", "confidence": "EXTRACTED", "source_file": "C:\\Users\\HP\\Desktop\\driprank\\src\\components\\leaderboard\\WeeklyTimer.jsx", "source_location": "L1", "weight": 1.0}, {"source": "c_users_hp_desktop_driprank_src_components_leaderboard_weeklytimer_jsx", "target": "lucide_react", "relation": "imports_from", "context": "import", "confidence": "EXTRACTED", "source_file": "C:\\Users\\HP\\Desktop\\driprank\\src\\components\\leaderboard\\WeeklyTimer.jsx", "source_location": "L2", "weight": 1.0}, {"source": "c_users_hp_desktop_driprank_src_components_leaderboard_weeklytimer_jsx", "target": "leaderboard_weeklytimer_getsecondsuntilmonday", "relation": "contains", "confidence": "EXTRACTED", "source_file": "C:\\Users\\HP\\Desktop\\driprank\\src\\components\\leaderboard\\WeeklyTimer.jsx", "source_location": "L4", "weight": 1.0}, {"source": "c_users_hp_desktop_driprank_src_components_leaderboard_weeklytimer_jsx", "target": "leaderboard_weeklytimer_fmt", "relation": "contains", "confidence": "EXTRACTED", "source_file": "C:\\Users\\HP\\Desktop\\driprank\\src\\components\\leaderboard\\WeeklyTimer.jsx", "source_location": "L14", "weight": 1.0}, {"source": "c_users_hp_desktop_driprank_src_components_leaderboard_weeklytimer_jsx", "target": "leaderboard_weeklytimer_seg", "relation": "contains", "confidence": "EXTRACTED", "source_file": "C:\\Users\\HP\\Desktop\\driprank\\src\\components\\leaderboard\\WeeklyTimer.jsx", "source_location": "L22", "weight": 1.0}, {"source": "c_users_hp_desktop_driprank_src_components_leaderboard_weeklytimer_jsx", "target": "leaderboard_weeklytimer_weeklytimer", "relation": "contains", "confidence": "EXTRACTED", "source_file": "C:\\Users\\HP\\Desktop\\driprank\\src\\components\\leaderboard\\WeeklyTimer.jsx", "source_location": "L35", "weight": 1.0}, {"source": "leaderboard_weeklytimer_weeklytimer", "target": "leaderboard_weeklytimer_fmt", "relation": "calls", "context": "call", "confidence": "EXTRACTED", "source_file": "C:\\Users\\HP\\Desktop\\driprank\\src\\components\\leaderboard\\WeeklyTimer.jsx", "source_location": "L43", "weight": 1.0}], "raw_calls": [{"caller_nid": "leaderboard_weeklytimer_getsecondsuntilmonday", "callee": "getDay", "is_member_call": true, "source_file": "C:\\Users\\HP\\Desktop\\driprank\\src\\components\\leaderboard\\WeeklyTimer.jsx", "source_location": "L7"}, {"caller_nid": "leaderboard_weeklytimer_getsecondsuntilmonday", "callee": "setDate", "is_member_call": true, "source_file": "C:\\Users\\HP\\Desktop\\driprank\\src\\components\\leaderboard\\WeeklyTimer.jsx", "source_location": "L9"}, {"caller_nid": "leaderboard_weeklytimer_getsecondsuntilmonday", "callee": "getDate", "is_member_call": true, "source_file": "C:\\Users\\HP\\Desktop\\driprank\\src\\components\\leaderboard\\WeeklyTimer.jsx", "source_location": "L9"}, {"caller_nid": "leaderboard_weeklytimer_getsecondsuntilmonday", "callee": "setHours", "is_member_call": true, "source_file": "C:\\Users\\HP\\Desktop\\driprank\\src\\components\\leaderboard\\WeeklyTimer.jsx", "source_location": "L10"}, {"caller_nid": "leaderboard_weeklytimer_getsecondsuntilmonday", "callee": "max", "is_member_call": true, "source_file": "C:\\Users\\HP\\Desktop\\driprank\\src\\components\\leaderboard\\WeeklyTimer.jsx", "source_location": "L11"}, {"caller_nid": "leaderboard_weeklytimer_getsecondsuntilmonday", "callee": "floor", "is_member_call": true, "source_file": "C:\\Users\\HP\\Desktop\\driprank\\src\\components\\leaderboard\\WeeklyTimer.jsx", "source_location": "L11"}, {"caller_nid": "leaderboard_weeklytimer_fmt", "callee": "floor", "is_member_call": true, "source_file": "C:\\Users\\HP\\Desktop\\driprank\\src\\components\\leaderboard\\WeeklyTimer.jsx", "source_location": "L15"}, {"caller_nid": "leaderboard_weeklytimer_fmt", "callee": "floor", "is_member_call": true, "source_file": "C:\\Users\\HP\\Desktop\\driprank\\src\\components\\leaderboard\\WeeklyTimer.jsx", "source_location": "L16"}, {"caller_nid": "leaderboard_weeklytimer_fmt", "callee": "floor", "is_member_call": true, "source_file": "C:\\Users\\HP\\Desktop\\driprank\\src\\components\\leaderboard\\WeeklyTimer.jsx", "source_location": "L17"}, {"caller_nid": "leaderboard_weeklytimer_seg", "callee": "padStart", "is_member_call": true, "source_file": "C:\\Users\\HP\\Desktop\\driprank\\src\\components\\leaderboard\\WeeklyTimer.jsx", "source_location": "L26"}, {"caller_nid": "leaderboard_weeklytimer_seg", "callee": "String", "is_member_call": false, "source_file": "C:\\Users\\HP\\Desktop\\driprank\\src\\components\\leaderboard\\WeeklyTimer.jsx", "source_location": "L26"}, {"caller_nid": "leaderboard_weeklytimer_weeklytimer", "callee": "useState", "is_member_call": false, "source_file": "C:\\Users\\HP\\Desktop\\driprank\\src\\components\\leaderboard\\WeeklyTimer.jsx", "source_location": "L36"}, {"caller_nid": "leaderboard_weeklytimer_weeklytimer", "callee": "useEffect", "is_member_call": false, "source_file": "C:\\Users\\HP\\Desktop\\driprank\\src\\components\\leaderboard\\WeeklyTimer.jsx", "source_location": "L38"}]}