{"nodes": [{"id": "c_users_hp_desktop_driprank_src_pages_admin_sections_designssection_jsx", "label": "DesignsSection.jsx", "file_type": "code", "source_file": "C:\\Users\\HP\\Desktop\\driprank\\src\\pages\\admin\\sections\\DesignsSection.jsx", "source_location": "L1"}, {"id": "sections_designssection_visibilitybadge", "label": "VisibilityBadge()", "file_type": "code", "source_file": "C:\\Users\\HP\\Desktop\\driprank\\src\\pages\\admin\\sections\\DesignsSection.jsx", "source_location": "L9"}, {"id": "sections_designssection_designrow", "label": "DesignRow()", "file_type": "code", "source_file": "C:\\Users\\HP\\Desktop\\driprank\\src\\pages\\admin\\sections\\DesignsSection.jsx", "source_location": "L15"}, {"id": "sections_designssection_adddesignmodal", "label": "AddDesignModal()", "file_type": "code", "source_file": "C:\\Users\\HP\\Desktop\\driprank\\src\\pages\\admin\\sections\\DesignsSection.jsx", "source_location": "L86"}, {"id": "sections_designssection_editdesignmodal", "label": "EditDesignModal()", "file_type": "code", "source_file": "C:\\Users\\HP\\Desktop\\driprank\\src\\pages\\admin\\sections\\DesignsSection.jsx", "source_location": "L185"}, {"id": "sections_designssection_designssection", "label": "DesignsSection()", "file_type": "code", "source_file": "C:\\Users\\HP\\Desktop\\driprank\\src\\pages\\admin\\sections\\DesignsSection.jsx", "source_location": "L266"}], "edges": [{"source": "c_users_hp_desktop_driprank_src_pages_admin_sections_designssection_jsx", "target": "react", "relation": "imports_from", "context": "import", "confidence": "EXTRACTED", "source_file": "C:\\Users\\HP\\Desktop\\driprank\\src\\pages\\admin\\sections\\DesignsSection.jsx", "source_location": "L1", "weight": 1.0}, {"source": "c_users_hp_desktop_driprank_src_pages_admin_sections_designssection_jsx", "target": "lucide_react", "relation": "imports_from", "context": "import", "confidence": "EXTRACTED", "source_file": "C:\\Users\\HP\\Desktop\\driprank\\src\\pages\\admin\\sections\\DesignsSection.jsx", "source_location": "L2", "weight": 1.0}, {"source": "c_users_hp_desktop_driprank_src_pages_admin_sections_designssection_jsx", "target": "c_users_hp_desktop_driprank_src_store_adminstore_js", "relation": "imports_from", "context": "import", "confidence": "EXTRACTED", "source_file": "C:\\Users\\HP\\Desktop\\driprank\\src\\pages\\admin\\sections\\DesignsSection.jsx", "source_location": "L6", "weight": 1.0}, {"source": "c_users_hp_desktop_driprank_src_pages_admin_sections_designssection_jsx", "target": "store_adminstore_useadminstore", "relation": "imports", "context": "import", "confidence": "EXTRACTED", "source_file": "C:\\Users\\HP\\Desktop\\driprank\\src\\pages\\admin\\sections\\DesignsSection.jsx", "source_location": "L6", "weight": 1.0}, {"source": "c_users_hp_desktop_driprank_src_pages_admin_sections_designssection_jsx", "target": "c_users_hp_desktop_driprank_src_store_toaststore_js", "relation": "imports_from", "context": "import", "confidence": "EXTRACTED", "source_file": "C:\\Users\\HP\\Desktop\\driprank\\src\\pages\\admin\\sections\\DesignsSection.jsx", "source_location": "L7", "weight": 1.0}, {"source": "c_users_hp_desktop_driprank_src_pages_admin_sections_designssection_jsx", "target": "store_toaststore_usetoaststore", "relation": "imports", "context": "import", "confidence": "EXTRACTED", "source_file": "C:\\Users\\HP\\Desktop\\driprank\\src\\pages\\admin\\sections\\DesignsSection.jsx", "source_location": "L7", "weight": 1.0}, {"source": "c_users_hp_desktop_driprank_src_pages_admin_sections_designssection_jsx", "target": "sections_designssection_visibilitybadge", "relation": "contains", "confidence": "EXTRACTED", "source_file": "C:\\Users\\HP\\Desktop\\driprank\\src\\pages\\admin\\sections\\DesignsSection.jsx", "source_location": "L9", "weight": 1.0}, {"source": "c_users_hp_desktop_driprank_src_pages_admin_sections_designssection_jsx", "target": "sections_designssection_designrow", "relation": "contains", "confidence": "EXTRACTED", "source_file": "C:\\Users\\HP\\Desktop\\driprank\\src\\pages\\admin\\sections\\DesignsSection.jsx", "source_location": "L15", "weight": 1.0}, {"source": "c_users_hp_desktop_driprank_src_pages_admin_sections_designssection_jsx", "target": "sections_designssection_adddesignmodal", "relation": "contains", "confidence": "EXTRACTED", "source_file": "C:\\Users\\HP\\Desktop\\driprank\\src\\pages\\admin\\sections\\DesignsSection.jsx", "source_location": "L86", "weight": 1.0}, {"source": "c_users_hp_desktop_driprank_src_pages_admin_sections_designssection_jsx", "target": "sections_designssection_editdesignmodal", "relation": "contains", "confidence": "EXTRACTED", "source_file": "C:\\Users\\HP\\Desktop\\driprank\\src\\pages\\admin\\sections\\DesignsSection.jsx", "source_location": "L185", "weight": 1.0}, {"source": "c_users_hp_desktop_driprank_src_pages_admin_sections_designssection_jsx", "target": "sections_designssection_designssection", "relation": "contains", "confidence": "EXTRACTED", "source_file": "C:\\Users\\HP\\Desktop\\driprank\\src\\pages\\admin\\sections\\DesignsSection.jsx", "source_location": "L266", "weight": 1.0}], "raw_calls": [{"caller_nid": "sections_designssection_designrow", "callee": "useState", "is_member_call": false, "source_file": "C:\\Users\\HP\\Desktop\\driprank\\src\\pages\\admin\\sections\\DesignsSection.jsx", "source_location": "L16"}, {"caller_nid": "sections_designssection_adddesignmodal", "callee": "useState", "is_member_call": false, "source_file": "C:\\Users\\HP\\Desktop\\driprank\\src\\pages\\admin\\sections\\DesignsSection.jsx", "source_location": "L87"}, {"caller_nid": "sections_designssection_adddesignmodal", "callee": "useState", "is_member_call": false, "source_file": "C:\\Users\\HP\\Desktop\\driprank\\src\\pages\\admin\\sections\\DesignsSection.jsx", "source_location": "L92"}, {"caller_nid": "sections_designssection_adddesignmodal", "callee": "useState", "is_member_call": false, "source_file": "C:\\Users\\HP\\Desktop\\driprank\\src\\pages\\admin\\sections\\DesignsSection.jsx", "source_location": "L93"}, {"caller_nid": "sections_designssection_editdesignmodal", "callee": "useState", "is_member_call": false, "source_file": "C:\\Users\\HP\\Desktop\\driprank\\src\\pages\\admin\\sections\\DesignsSection.jsx", "source_location": "L186"}, {"caller_nid": "sections_designssection_editdesignmodal", "callee": "useState", "is_member_call": false, "source_file": "C:\\Users\\HP\\Desktop\\driprank\\src\\pages\\admin\\sections\\DesignsSection.jsx", "source_location": "L194"}, {"caller_nid": "sections_designssection_designssection", "callee": "useAdminStore", "is_member_call": false, "source_file": "C:\\Users\\HP\\Desktop\\driprank\\src\\pages\\admin\\sections\\DesignsSection.jsx", "source_location": "L267"}, {"caller_nid": "sections_designssection_designssection", "callee": "useAdminStore", "is_member_call": false, "source_file": "C:\\Users\\HP\\Desktop\\driprank\\src\\pages\\admin\\sections\\DesignsSection.jsx", "source_location": "L268"}, {"caller_nid": "sections_designssection_designssection", "callee": "useAdminStore", "is_member_call": false, "source_file": "C:\\Users\\HP\\Desktop\\driprank\\src\\pages\\admin\\sections\\DesignsSection.jsx", "source_location": "L269"}, {"caller_nid": "sections_designssection_designssection", "callee": "useAdminStore", "is_member_call": false, "source_file": "C:\\Users\\HP\\Desktop\\driprank\\src\\pages\\admin\\sections\\DesignsSection.jsx", "source_location": "L270"}, {"caller_nid": "sections_designssection_designssection", "callee": "useToastStore", "is_member_call": false, "source_file": "C:\\Users\\HP\\Desktop\\driprank\\src\\pages\\admin\\sections\\DesignsSection.jsx", "source_location": "L271"}, {"caller_nid": "sections_designssection_designssection", "callee": "useState", "is_member_call": false, "source_file": "C:\\Users\\HP\\Desktop\\driprank\\src\\pages\\admin\\sections\\DesignsSection.jsx", "source_location": "L273"}, {"caller_nid": "sections_designssection_designssection", "callee": "useState", "is_member_call": false, "source_file": "C:\\Users\\HP\\Desktop\\driprank\\src\\pages\\admin\\sections\\DesignsSection.jsx", "source_location": "L274"}, {"caller_nid": "sections_designssection_designssection", "callee": "useState", "is_member_call": false, "source_file": "C:\\Users\\HP\\Desktop\\driprank\\src\\pages\\admin\\sections\\DesignsSection.jsx", "source_location": "L275"}, {"caller_nid": "sections_designssection_designssection", "callee": "useState", "is_member_call": false, "source_file": "C:\\Users\\HP\\Desktop\\driprank\\src\\pages\\admin\\sections\\DesignsSection.jsx", "source_location": "L276"}, {"caller_nid": "sections_designssection_designssection", "callee": "filter", "is_member_call": true, "source_file": "C:\\Users\\HP\\Desktop\\driprank\\src\\pages\\admin\\sections\\DesignsSection.jsx", "source_location": "L278"}, {"caller_nid": "sections_designssection_designssection", "callee": "map", "is_member_call": true, "source_file": "C:\\Users\\HP\\Desktop\\driprank\\src\\pages\\admin\\sections\\DesignsSection.jsx", "source_location": "L346"}, {"caller_nid": "sections_designssection_designssection", "callee": "map", "is_member_call": true, "source_file": "C:\\Users\\HP\\Desktop\\driprank\\src\\pages\\admin\\sections\\DesignsSection.jsx", "source_location": "L367"}]}